[
	{
		"name": "Coffee",
		"description": null,
		"location": null,
		"footnote": "A daily cup of black coffee always make my day.",
		"tooltip": null,
		"category": null,
		"language": null,
		"link": null,
		"linkedTitle": false
	},
	{
		"name": "Films & TV Drama",
		"description": null,
		"location": null,
		"footnote": "Almost anything except scary or non-sci-fi horror films or romamce drama.",
		"tooltip": "Have Disney+ and Netflix subscriptions as well!",
		"category": null,
		"language": null,
		"link": null,
		"linkedTitle": false
	},
	{
		"name": "Music",
		"description": null,
		"location": null,
		"footnote": "Classical, film soundtracks, western oldies, sometimes jazz and country songs.",
		"tooltip": "Actually I did learned amateur classic piano for over 20 years as a hobby.",
		"category": null,
		"language": null,
		"link": null,
		"linkedTitle": false
	},
	{
		"name": "Reading",
		"description": null,
		"location": null,
		"footnote": "Science fiction, fantasy, literature and a few non-fiction.",
		"tooltip": null,
		"category": null,
		"language": null,
		"link": null,
		"linkedTitle": false
	},
	{
		"name": "PC Gaming",
		"description": null,
		"location": null,
		"footnote": "Both AAA and indie games.",
		"tooltip": null,
		"category": null,
		"language": null,
		"link": null,
		"linkedTitle": false
	},
	{
		"name": "Maker projects",
		"description": null,
		"location": null,
		"footnote": "Building fun and interactive DIY devices.",
		"tooltip": "You can find some examples in the portfolio.",
		"category": null,
		"language": null,
		"link": null,
		"linkedTitle": false
	},
	{
		"name": "Photography & film camera collecting",
		"description": null,
		"location": null,
		"footnote": "Both digital and film (35mm, 120, Polaroid). I also collected a couple dozen of vintage cameras.",
		"tooltip": null,
		"category": null,
		"language": null,
		"link": null,
		"linkedTitle": false
	},
	{
		"name": "Watch collecting",
		"description": null,
		"location": null,
		"footnote": "(Budget) mechanical watches. Try to stay practical though.",
		"tooltip": null,
		"category": null,
		"language": null,
		"link": null,
		"linkedTitle": false
	}
]
